bsym/__init__.py
bsym/bsym.py
bsym/colour_operation.py
bsym/configuration.py
bsym/configuration_space.py
bsym/coordinate_config_space.py
bsym/permutations.py
bsym/point_group.py
bsym/space_group.py
bsym/symmetry_group.py
bsym/symmetry_operation.py
bsym/version.py
bsym/interface/__init__.py
bsym/interface/pymatgen.py
bsym-1.2.0.dist-info/LICENSE
bsym-1.2.0.dist-info/METADATA
bsym-1.2.0.dist-info/WHEEL
bsym-1.2.0.dist-info/top_level.txt
bsym-1.2.0.dist-info/RECORD
