Metadata-Version: 2.1
Name: bsym
Version: 1.2.0
Summary: A Basic Symmetry Module
Home-page: https://github.com/bjmorgan/bsym
Author: Benjamin J. Morgan
Author-email: b.j.morgan@bath.ac.uk
License: MIT
Download-URL: https://github.com/bjmorgan/bsym/archive/1.2.0.tar.gz
Platform: UNKNOWN
Requires-Python: >=3.5
Requires-Dist: pymatgen (>=v2017.10.16)
Requires-Dist: numpy
Requires-Dist: tqdm
